tree_struct_config/__init__.py
tree_struct_config/core.py
tree_struct_config/core2.py
tree_struct_config/exceptiones.py
TreeStructConfig-0.2.3.dist-info/METADATA
TreeStructConfig-0.2.3.dist-info/WHEEL
TreeStructConfig-0.2.3.dist-info/top_level.txt
TreeStructConfig-0.2.3.dist-info/RECORD
