Metadata-Version: 2.1
Name: TreeStructConfig
Version: 0.2.3
Summary: A Tree Struct Configuration module for python, support serialization to/from JSON and TOML
Home-page: https://github.com/rexzhang/tree-struct-config
Author: Rex Zhang
Author-email: rex.zhang@gmail.com
License: MIT
Keywords: configuration json
Platform: UNKNOWN
Classifier: Development Status :: 4 - Beta
Classifier: License :: OSI Approved :: MIT License
Classifier: Programming Language :: Python :: 3.4
Classifier: Programming Language :: Python :: 3.5
Classifier: Programming Language :: Python :: 3.6
Classifier: Programming Language :: Python :: 3.7
Classifier: Topic :: Software Development :: Libraries :: Python Modules
Requires-Python: >=3.4
Provides-Extra: toml
Requires-Dist: toml ; extra == 'toml'
